{
  "category": "救急医学全般",
  "questions": [
    {
      "id": "general_em_entry_001",
      "question": "ショックの定義として最も適切なのはどれか。",
      "choices": [
        "収縮期血圧90mmHg未満",
        "組織への酸素供給不足",
        "脈拍100回/分以上",
        "意識レベル低下"
      ],
      "answers": [1],
      "selectCount": 1,
      "explanation": "ショックとは、循環不全により組織への酸素供給が需要を満たせず、細胞障害や臓器障害に至りうる状態である。低血圧、頻脈、意識障害はショックでみられる所見だが、それ自体がショックの定義ではない。血圧が保たれていても、末梢冷感、皮膚蒼白、尿量低下、乳酸上昇、意識障害などがあれば代償性ショックを疑う。"
    },
    {
      "id": "general_em_entry_002",
      "question": "SpO2モニタリングと酸素投与について、誤っているものはどれか。",
      "choices": [
        "表示には遅れがある",
        "SpO2 90%前後ではPaO2は大きく低下しうる",
        "全患者でSpO2 100%を目標にする",
        "COPDでは88〜92%を目標にすることがある"
      ],
      "answers": [2],
      "selectCount": 1,
      "explanation": "SpO2は有用な連続モニタリング指標だが、表示には機器の平均化時間や末梢循環の影響があり、現在の体内酸素化を完全なリアルタイムで反映するとは限らない。また酸素解離曲線の性質上、SpO2 90%前後ではPaO2は約60mmHg程度まで低下していることがあり、そこからさらにSpO2が少し下がるだけでもPaO2は大きく低下しうる。酸素は薬剤として扱い、漫然とSpO2 100%を目標にしない。急性期成人で高二酸化炭素血症リスクがなければSpO2 94〜98%程度、COPDなど高二酸化炭素血症リスクがある場合は88〜92%程度を目標にすることがある。"
    },
    {
      "id": "general_em_entry_003",
      "question": "成人BLS/ICLSにおける心肺蘇生の手技・数値として正しいものはどれか。",
      "choices": [
        "胸骨圧迫と人工呼吸は30:2",
        "圧迫の深さは約2cm",
        "圧迫テンポは60〜80回/分",
        "除細動直後に脈拍を30秒かけて確認する"
      ],
      "answers": [0],
      "selectCount": 1,
      "explanation": "成人BLSでは、気道確保器具がない場合、胸骨圧迫30回に対して人工呼吸2回の30:2を基本とする。胸骨圧迫は胸骨下半分を、約5cm沈む深さで、6cmを超えないように、100〜120回/分のテンポで行う。除細動後は長く脈拍確認を行わず、直ちに胸骨圧迫を再開して中断時間を最小限にする。"
    },
    {
      "id": "general_em_entry_004",
      "question": "災害現場でSTART法による一次トリアージを行う。30歳男性。自力歩行不能。呼吸数22回/分。橈骨動脈触知可能。指示に従える。左下腿に変形と疼痛あり。最も適切な区分はどれか。",
      "choices": [
        "黒",
        "赤",
        "黄",
        "緑"
      ],
      "answers": [2],
      "selectCount": 1,
      "explanation": "START法では、まず自力歩行できる傷病者を緑とする。自力歩行できない場合、呼吸、循環、意識を評価する。呼吸数異常、循環不良、指示に従えない場合は赤となる。本症例は自力歩行できないが、呼吸数22回/分、橈骨動脈触知可能、指示動作可能であり、赤の基準を満たさないため黄と判断する。骨折が疑われるため軽症の緑ではなく、待機的治療群として扱う。"
    },
    {
      "id": "general_em_entry_005",
      "question": "18歳の喘息既往患者。朝から喘鳴があり、SpO2 96%、呼吸数20/分、呼吸様式は軽度努力呼吸、両肺にwheezingを認める。まず行うべき治療はどれか。",
      "choices": [
        "ソルメドロール 125mg 点滴投与",
        "ボスミン 0.1mL＋生理食塩水 1mL 吸入",
        "ソルメドロール 40mg 点滴投与",
        "ベネトリン 0.5mL＋生理食塩水 1mL 吸入",
        "ボスミン 0.5mL＋生理食塩水 1mL 吸入"
      ],
      "answers": [3],
      "selectCount": 1,
      "explanation": "喘息発作で喘鳴を認めるが、SpO2 96%、呼吸数20/分、軽度努力呼吸であれば、まず短時間作用性β2刺激薬であるサルブタモール（ベネトリン）吸入を行う。ベネトリンは通常、生理食塩水で希釈してネブライザー吸入する。全身性ステロイドは中等症以上、吸入反応不良、増悪リスクが高い場合などに早期併用を検討する。アドレナリン吸入は喘息の通常初期治療ではなく、上気道狭窄やアナフィラキシーなど別の病態で検討される。"
    }
  ]
}